libdlfind/__init__.py
libdlfind/callback.py
libdlfind/function_types.py
libdlfind/lib.py
libdlfind/libdlfind.dll
libdlfind/libdlfind.dll.a
libdlfind-0.0.3.dist-info/COPYING
libdlfind-0.0.3.dist-info/COPYING.LESSER
libdlfind-0.0.3.dist-info/LICENSE_bundled.txt
libdlfind-0.0.3.dist-info/METADATA
libdlfind-0.0.3.dist-info/WHEEL
libdlfind-0.0.3.dist-info/top_level.txt
libdlfind-0.0.3.dist-info/RECORD
