Metadata-Version: 2.1
Name: libdlfind
Version: 0.0.3
Summary: Python library for DL-FIND
Home-page: https://github.com/kjelljorner/libdlfind
Author: Kjell Jorner
Author-email: kjell.jorner@gmail.com
License: LGPLv3
Classifier: Programming Language :: Python :: 3
Classifier: License :: OSI Approved :: GNU General Public License v3 or later (GPLv3+)
Classifier: Operating System :: OS Independent
Requires-Python: >=3.8
License-File: LICENSE_bundled.txt
License-File: COPYING
License-File: COPYING.LESSER
